pyrseus/__init__.py
pyrseus/interactive.py
pyrseus/core/__init__.py
pyrseus/core/pickle.py
pyrseus/core/sys.py
pyrseus/ctx/__init__.py
pyrseus/ctx/api.py
pyrseus/ctx/mgr.py
pyrseus/ctx/registry.py
pyrseus/ctx/simple.py
pyrseus/ctx/plugins/__init__.py
pyrseus/ctx/plugins/cpinline.py
pyrseus/ctx/plugins/cpmpi4py.py
pyrseus/ctx/plugins/cpnocatch.py
pyrseus/ctx/plugins/cpprocess.py
pyrseus/ctx/plugins/inline.py
pyrseus/ctx/plugins/ipyparallel.py
pyrseus/ctx/plugins/loky.py
pyrseus/ctx/plugins/mpi4py.py
pyrseus/ctx/plugins/nocatch.py
pyrseus/ctx/plugins/pinline.py
pyrseus/ctx/plugins/pnocatch.py
pyrseus/ctx/plugins/process.py
pyrseus/ctx/plugins/thread.py
pyrseus/executors/__init__.py
pyrseus/executors/cpinline.py
pyrseus/executors/cpnocatch.py
pyrseus/executors/cpprocess.py
pyrseus/executors/inline.py
pyrseus/executors/nocatch.py
pyrseus/executors/pinline.py
pyrseus/executors/pnocatch.py
pyrseus-0.1.0.dist-info/METADATA
pyrseus-0.1.0.dist-info/WHEEL
pyrseus-0.1.0.dist-info/RECORD
