Metadata-Version: 2.3
Name: pyrseus
Version: 0.1.0
Summary: ExecutorCtx factory, its plugins, and various serial Executors
Project-URL: Homepage, https://github.com/dalleyg/pyrseus
Project-URL: Issues, https://github.com/dalleyg/pyrseus/issues
Author: Gerald Dalley
License-Expression: MIT
Keywords: Executor,ExecutorCtx,InlineExecutor,NoCatchExecutor,concurrent.futures,executor
Classifier: Development Status :: 4 - Beta
Classifier: Intended Audience :: Developers
Classifier: License :: OSI Approved :: MIT License
Classifier: Operating System :: OS Independent
Classifier: Programming Language :: Python :: 3
Classifier: Programming Language :: Python :: 3.9
Classifier: Programming Language :: Python :: 3.10
Classifier: Programming Language :: Python :: 3.11
Classifier: Programming Language :: Python :: 3.12
Classifier: Topic :: Software Development :: Libraries
Requires-Python: >=3.9
Requires-Dist: cloudpickle>=1.6.0
Requires-Dist: psutil
Provides-Extra: ipyparallel
Requires-Dist: ipyparallel; extra == 'ipyparallel'
Provides-Extra: loky
Requires-Dist: loky; extra == 'loky'
Provides-Extra: mpi4py
Requires-Dist: mpi4py>=3.0.0; extra == 'mpi4py'
